{
	"apiVersion": 3,
	"title": "events",
	"description": "this is for events",
	"text-domain": "aquamin",
	"name": "aquamin/events",
	"icon": "feedback",
	"category": "aquamin-blocks",
	"example": {},
	"attributes": {
		"aquaminClassNameAni": {
			"type": "array",
			"default": []
		},
		"aquaminClassNameHide": {
			"type": "array",
			"default": []
		}
	},
	"supports": {
		"customClassName": true,
		"align": ["wide", "full"],
		"spacing": {
			"margin": ["top", "bottom"],
			"padding": ["top", "bottom"]
		}
	}
}
